{"run_id": 2805, "bias_std_dev_scale": 0.170998, "bias_height_fraction": 0.119897, "perturbation_size": 0.005, "optimizer": "FIRE", "found_minima": [[0.6234994049, 0.02803775853], [-0.050011180578091556, 0.4666941780118899], [-0.558223649310609, 1.441725827372356]], "found_saddles": [[0.20652128349880575, 0.298914908626844], [-0.8591268876753797, 0.5023789339876886]], "bias_count": 45, "energy_calls_at_each_min": [1, 755, 5632], "force_calls_at_each_min": [1, 755, 5632], "min_height_scale": 2.0, "max_height_scale": 3.0, "min_cov_scale": 2.5, "max_cov_scale": 2.5, "pert_type": "adaptive"}